wallet_pass/__init__.py
wallet_pass/apple/__init__.py
wallet_pass/apple/constants.py
wallet_pass/apple/main.py
wallet_pass/apple/schemas.py
wallet_pass/google/__init__.py
wallet_pass/main.py
wallet_pass-0.1.2.dist-info/LICENSE
wallet_pass-0.1.2.dist-info/METADATA
wallet_pass-0.1.2.dist-info/WHEEL
wallet_pass-0.1.2.dist-info/RECORD
